mlbi_at_dku_lib/__init__.py
mlbi_at_dku_lib/cpdb.py
mlbi_at_dku_lib/deiso.py
mlbi_at_dku_lib/hicat.py
mlbi_at_dku_lib/icnv.py
mlbi_at_dku_lib/misc.py
mlbi_at_dku_lib/data/GTmap_hg19.csv
mlbi_at_dku_lib/data/GTmap_hg38.csv
mlbi_at_dku_lib/data/GTmap_mm10.csv
mlbi_at_dku_lib-0.3.9.dist-info/LICENSE
mlbi_at_dku_lib-0.3.9.dist-info/METADATA
mlbi_at_dku_lib-0.3.9.dist-info/WHEEL
mlbi_at_dku_lib-0.3.9.dist-info/entry_points.txt
mlbi_at_dku_lib-0.3.9.dist-info/top_level.txt
mlbi_at_dku_lib-0.3.9.dist-info/RECORD
