Metadata-Version: 2.1
Name: mlbi-at-dku-lib
Version: 0.3.9
Summary: Toolkits for single-cell RNA-Seq data analysis. (Wrapper functions for CellPhoneDB, GSEApy and InferCNVpy)
Author-email: Seokhyun Yoon <syoon@dku.edu>
License: MIT License
Project-URL: Homepage, https://github.com/combio-dku
Keywords: single-cell RNA-seq,bioinformatics
Classifier: Programming Language :: Python
Classifier: Programming Language :: Python :: 3
Classifier: License :: OSI Approved :: MIT License
License-File: LICENSE
Provides-Extra: dev
Requires-Dist: numpy ; extra == 'dev'
Requires-Dist: pandas ; extra == 'dev'
Requires-Dist: scipy ; extra == 'dev'
Requires-Dist: scikit-learn ; extra == 'dev'
Requires-Dist: scikit-network ; extra == 'dev'
